tm2d/__init__.py
tm2d/cross_correlation.py
tm2d/ctf.py
tm2d/micrograph.py
tm2d/orientation_sampling.py
tm2d/plan.py
tm2d/plan_standard.py
tm2d/results_per_param.py
tm2d/results_per_pixel.py
tm2d/template_atomic.py
tm2d/template_density.py
tm2d/simulators/image.py
tm2d/simulators/transfer_function.py
tm2d/utilities/__init__.py
tm2d/utilities/fftshift_util.py
tm2d/utilities/file_loading.py
tm2d/utilities/image_processing.py
tm2d/utilities/optics_functions.py
tm2d/utilities/rotation_matricies.py
tm2d/utilities/signal_normalization.py
tm2d/utilities/whitener.py
tm2d-0.1.3.dist-info/licenses/LICENSE
tm2d-0.1.3.dist-info/METADATA
tm2d-0.1.3.dist-info/WHEEL
tm2d-0.1.3.dist-info/top_level.txt
tm2d-0.1.3.dist-info/RECORD
