Metadata-Version: 2.4
Name: tm2d
Version: 0.1.3
Summary: A Python module for orchestrating and dispatching large computations across multi-GPU systems using Vulkan.
Author-email: Shahar Sandhaus <shahar.sandhaus@berkeley.edu>
Project-URL: Homepage, https://github.com/sharhar/tm2d
Project-URL: Issues, https://github.com/sharhar/tm2d/issues
Classifier: Programming Language :: Python :: 3
Classifier: License :: OSI Approved :: MIT License
Classifier: Operating System :: OS Independent
Classifier: Development Status :: 2 - Pre-Alpha
Requires-Python: >=3.9
License-File: LICENSE
Requires-Dist: setuptools>=59.0
Requires-Dist: numpy
Requires-Dist: vkdispatch==0.0.28
Provides-Extra: healpy
Requires-Dist: healpy; extra == "healpy"
Dynamic: license-file
